photocrawl/__init__.py
photocrawl/__main__.py
photocrawl/photocrawl.py
photocrawl/plotting_functions.py
photocrawl/utils.py
photocrawl-0.3.2.dist-info/METADATA
photocrawl-0.3.2.dist-info/WHEEL
photocrawl-0.3.2.dist-info/licenses/LICENSE
photocrawl-0.3.2.dist-info/RECORD
