Metadata-Version: 2.3
Name: photocrawl
Version: 0.3.2
Summary: Package for analysis of photography habits.
Project-URL: homepage, https://github.com/fsoubelet/PhotoCrawl
Project-URL: repository, https://github.com/fsoubelet/PhotoCrawl
Project-URL: documentation, https://fsoubelet.github.io/PhotoCrawl/
Author-email: Felix Soubelet <felix.soubelet@cern.ch>
License-Expression: MIT
License-File: LICENSE
Keywords: Photography,Utility,Visualisation
Classifier: Development Status :: 4 - Beta
Classifier: License :: OSI Approved :: MIT License
Classifier: Natural Language :: English
Classifier: Programming Language :: Python
Classifier: Programming Language :: Python :: 3 :: Only
Classifier: Programming Language :: Python :: 3.9
Classifier: Programming Language :: Python :: 3.10
Classifier: Programming Language :: Python :: 3.11
Classifier: Programming Language :: Python :: 3.12
Classifier: Programming Language :: Python :: Implementation :: CPython
Classifier: Topic :: Scientific/Engineering :: Visualization
Classifier: Topic :: Utilities
Requires-Python: >=3.9
Requires-Dist: loguru<1.0
Requires-Dist: matplotlib>=3.8
Requires-Dist: pandas>=2.1
Requires-Dist: pendulum>=2.1
Requires-Dist: pillow>=10.0
Requires-Dist: pyexifinfo>=0.4
Requires-Dist: seaborn>=0.12
Requires-Dist: typer>=0.10
